pg_xades-0.0.7.dist-info/DESCRIPTION.rst
pg_xades-0.0.7.dist-info/METADATA
pg_xades-0.0.7.dist-info/RECORD
pg_xades-0.0.7.dist-info/WHEEL
pg_xades-0.0.7.dist-info/metadata.json
pg_xades-0.0.7.dist-info/top_level.txt
pgxades/__init__.py
pgxades/constants.py
pgxades/ns.py
pgxades/policy.py
pgxades/template.py
pgxades/utils.py
pgxades/xades_context.py
pgxades/data/XAdES.xsd
pgxades/data/xmldsig-core-schema.xsd
